binance_mcp_server/README.md
binance_mcp_server/__init__.py
binance_mcp_server/__main__.py
binance_mcp_server/binance_api.py
binance_mcp_server/binance_ws_api.py
binance_mcp_server/server.py
binance_mcp_server/commands/__init__.py
binance_mcp_server/commands/market_data.py
binance_mcp_server/commands/market_info.py
binance_mcp_server/commands/websocket_streams.py
iflow_mcp_tienan92it_binance_mcp-0.1.0.dist-info/METADATA
iflow_mcp_tienan92it_binance_mcp-0.1.0.dist-info/WHEEL
iflow_mcp_tienan92it_binance_mcp-0.1.0.dist-info/licenses/LICENSE
iflow_mcp_tienan92it_binance_mcp-0.1.0.dist-info/RECORD
