Metadata-Version: 2.4
Name: iflow-mcp_tienan92it-binance-mcp
Version: 0.1.0
Summary: MCP server for accessing Binance data
License-File: LICENSE
Requires-Python: >=3.8
Requires-Dist: mcp>=1.6.0
Requires-Dist: requests>=2.28.0
Requires-Dist: uvicorn>=0.30.0
Requires-Dist: websockets>=11.0.0
